imagination/__init__.py
imagination/controller.py
imagination/core.py
imagination/debug.py
imagination/exc.py
imagination/exception.py
imagination/loader.py
imagination/standalone.py
imagination/wrapper.py
imagination/assembler/__init__.py
imagination/assembler/abstract.py
imagination/assembler/core.py
imagination/assembler/handlers.py
imagination/assembler/xml.py
imagination/decorator/__init__.py
imagination/decorator/config.py
imagination/decorator/helper.py
imagination/decorator/service.py
imagination/decorator/validator.py
imagination/helper/__init__.py
imagination/helper/context.py
imagination/helper/general.py
imagination/helper/id_naming.py
imagination/helper/transformer.py
imagination/meta/__init__.py
imagination/meta/container.py
imagination/meta/definition.py
imagination-3.4.5.dist-info/METADATA
imagination-3.4.5.dist-info/WHEEL
imagination-3.4.5.dist-info/top_level.txt
imagination-3.4.5.dist-info/RECORD
